<?xml version="1.0" encoding="UTF-8"?>
<GenRun Id="synth_1" LaunchPart="xc7a35tcpg236-1" LaunchTime="1673440559">
  <File Type="PA-TCL" Name="top.tcl"/>
  <File Type="REPORTS-TCL" Name="top_reports.tcl"/>
  <File Type="RDS-RDS" Name="top.vds"/>
  <File Type="RDS-UTIL" Name="top_utilization_synth.rpt"/>
  <File Type="RDS-UTIL-PB" Name="top_utilization_synth.pb"/>
  <File Type="RDS-DCP" Name="top.dcp"/>
  <FileSet Name="sources" Type="DesignSrcs" RelSrcDir="$PSRCDIR/sources_1" RelGenDir="$PGENDIR/sources_1">
    <Filter Type="Srcs"/>
    <File Path="$PSRCDIR/sources_1/imports/Keyboard Sample Code/KeyboardDecoder.v">
      <FileInfo>
        <Attr Name="ImportPath" Val="$PPRDIR/../../清大/邏輯設計實驗/Keyboard Sample Code/Keyboard Sample Code/KeyboardDecoder.v"/>
        <Attr Name="ImportTime" Val="1668754060"/>
        <Attr Name="UsedIn" Val="synthesis"/>
        <Attr Name="UsedIn" Val="implementation"/>
        <Attr Name="UsedIn" Val="simulation"/>
      </FileInfo>
    </File>
    <File Path="$PSRCDIR/sources_1/imports/Keyboard Sample Code/OnePulse.v">
      <FileInfo>
        <Attr Name="ImportPath" Val="$PPRDIR/../../清大/邏輯設計實驗/Keyboard Sample Code/Keyboard Sample Code/OnePulse.v"/>
        <Attr Name="ImportTime" Val="1668754060"/>
        <Attr Name="UsedIn" Val="synthesis"/>
        <Attr Name="UsedIn" Val="implementation"/>
        <Attr Name="UsedIn" Val="simulation"/>
      </FileInfo>
    </File>
    <File Path="$PSRCDIR/sources_1/imports/Keyboard Sample Code/SampleDisplay.v">
      <FileInfo>
        <Attr Name="ImportPath" Val="$PPRDIR/../../清大/邏輯設計實驗/Keyboard Sample Code/Keyboard Sample Code/SampleDisplay.v"/>
        <Attr Name="ImportTime" Val="1668754060"/>
        <Attr Name="UsedIn" Val="synthesis"/>
        <Attr Name="UsedIn" Val="implementation"/>
        <Attr Name="UsedIn" Val="simulation"/>
      </FileInfo>
    </File>
    <File Path="$PPRDIR/../../Tetris_2.v">
      <FileInfo>
        <Attr Name="UsedIn" Val="synthesis"/>
        <Attr Name="UsedIn" Val="implementation"/>
        <Attr Name="UsedIn" Val="simulation"/>
      </FileInfo>
    </File>
    <File Path="$PSRCDIR/sources_1/imports/demo1/clock_divisor.v">
      <FileInfo>
        <Attr Name="ImportPath" Val="$PPRDIR/../../清大/邏輯設計實驗/final_project/VGA/DEMO/demo1/clock_divisor.v"/>
        <Attr Name="ImportTime" Val="1669879792"/>
        <Attr Name="UsedIn" Val="synthesis"/>
        <Attr Name="UsedIn" Val="implementation"/>
        <Attr Name="UsedIn" Val="simulation"/>
      </FileInfo>
    </File>
    <File Path="$PSRCDIR/sources_1/new/next_block_generator.v">
      <FileInfo>
        <Attr Name="UsedIn" Val="synthesis"/>
        <Attr Name="UsedIn" Val="implementation"/>
        <Attr Name="UsedIn" Val="simulation"/>
      </FileInfo>
    </File>
    <File Path="$PSRCDIR/sources_1/imports/demo1/vga.v">
      <FileInfo>
        <Attr Name="ImportPath" Val="$PPRDIR/../../清大/邏輯設計實驗/final_project/VGA/DEMO/demo1/vga.v"/>
        <Attr Name="ImportTime" Val="1669879793"/>
        <Attr Name="UsedIn" Val="synthesis"/>
        <Attr Name="UsedIn" Val="implementation"/>
        <Attr Name="UsedIn" Val="simulation"/>
      </FileInfo>
    </File>
    <File Path="$PSRCDIR/sources_1/new/Top.v">
      <FileInfo>
        <Attr Name="UsedIn" Val="synthesis"/>
        <Attr Name="UsedIn" Val="implementation"/>
        <Attr Name="UsedIn" Val="simulation"/>
      </FileInfo>
    </File>
    <File Path="$PPRDIR/../../../final_project/final_project.srcs/pixel_generator.v">
      <FileInfo>
        <Attr Name="AutoDisabled" Val="1"/>
        <Attr Name="UsedIn" Val="synthesis"/>
        <Attr Name="UsedIn" Val="implementation"/>
        <Attr Name="UsedIn" Val="simulation"/>
      </FileInfo>
    </File>
    <File Path="$PSRCDIR/sources_1/new/text_Tetris.v">
      <FileInfo>
        <Attr Name="AutoDisabled" Val="1"/>
        <Attr Name="UsedIn" Val="synthesis"/>
        <Attr Name="UsedIn" Val="implementation"/>
        <Attr Name="UsedIn" Val="simulation"/>
      </FileInfo>
    </File>
    <File Path="$PSRCDIR/sources_1/new/test_next_block_generator.v">
      <FileInfo>
        <Attr Name="AutoDisabled" Val="1"/>
        <Attr Name="UsedIn" Val="synthesis"/>
        <Attr Name="UsedIn" Val="implementation"/>
        <Attr Name="UsedIn" Val="simulation"/>
      </FileInfo>
    </File>
    <Config>
      <Option Name="DesignMode" Val="RTL"/>
      <Option Name="TopModule" Val="top"/>
    </Config>
  </FileSet>
  <FileSet Name="constrs_in" Type="Constrs" RelSrcDir="$PSRCDIR/constrs_1">
    <Filter Type="Constrs"/>
    <File Path="$PSRCDIR/constrs_1/imports/demo1/Basys3_Master.xdc">
      <FileInfo>
        <Attr Name="ImportPath" Val="$PPRDIR/../../清大/邏輯設計實驗/final_project/VGA/DEMO/demo1/Basys3_Master.xdc"/>
        <Attr Name="ImportTime" Val="1669879792"/>
        <Attr Name="UsedIn" Val="synthesis"/>
        <Attr Name="UsedIn" Val="implementation"/>
      </FileInfo>
    </File>
    <File Path="$PSRCDIR/constrs_1/imports/Keyboard Sample Code/KeyboardConstraints.xdc">
      <FileInfo>
        <Attr Name="ImportPath" Val="$PPRDIR/../../清大/邏輯設計實驗/Keyboard Sample Code/Keyboard Sample Code/KeyboardConstraints.xdc"/>
        <Attr Name="ImportTime" Val="1668754060"/>
        <Attr Name="UsedIn" Val="synthesis"/>
        <Attr Name="UsedIn" Val="implementation"/>
      </FileInfo>
    </File>
    <Config>
      <Option Name="ConstrsType" Val="XDC"/>
    </Config>
  </FileSet>
  <FileSet Name="utils" Type="Utils" RelSrcDir="$PSRCDIR/utils_1">
    <Filter Type="Utils"/>
    <Config>
      <Option Name="TopAutoSet" Val="TRUE"/>
    </Config>
  </FileSet>
  <Strategy Version="1" Minor="2">
    <StratHandle Name="Vivado Synthesis Defaults" Flow="Vivado Synthesis 2020"/>
    <Step Id="synth_design"/>
  </Strategy>
  <BlockFileSet Type="BlockSrcs" Name="KeyboardCtrl_0"/>
</GenRun>
